recap_argument_graph/__init__.py
recap_argument_graph/dt.py
recap_argument_graph/edge.py
recap_argument_graph/graph.py
recap_argument_graph/node.py
recap_argument_graph/py.typed
recap_argument_graph/utils.py
recap_argument_graph-0.1.45.dist-info/LICENSE
recap_argument_graph-0.1.45.dist-info/WHEEL
recap_argument_graph-0.1.45.dist-info/METADATA
recap_argument_graph-0.1.45.dist-info/RECORD
